djadmin/__init__.py
djadmin/admin.py
djadmin/apps.py
djadmin/colors.py
djadmin/forms.py
djadmin/middleware.py
djadmin/mixins.py
djadmin/models.py
djadmin/settings.py
djadmin/sidebar.py
djadmin/signals.py
djadmin/tests.py
djadmin/urls.py
djadmin/util.py
djadmin/views.py
djadmin/migrations/0001_initial.py
djadmin/migrations/0002_auto_20170128_1519.py
djadmin/migrations/0003_auto_20170324_0011.py
djadmin/migrations/__init__.py
djadmin/static/admin/css/custom.css
djadmin/static/admin/css/custom.min.css
djadmin/static/admin/css/materialize.min.css
djadmin/static/admin/css/prism.css
djadmin/static/admin/font/material-design-icons/Material-Design-Icons.svg
djadmin/static/admin/font/material-design-icons/Material-Design-Icons.ttf
djadmin/static/admin/font/material-design-icons/Material-Design-Icons.woff
djadmin/static/admin/font/material-design-icons/Material-Design-Icons.woff2
djadmin/static/admin/font/material-design-icons/Material-Design-Iconsd41d.eot
djadmin/static/admin/font/roboto/Roboto-Bold.ttf
djadmin/static/admin/font/roboto/Roboto-Bold.woff
djadmin/static/admin/font/roboto/Roboto-Bold.woff2
djadmin/static/admin/font/roboto/Roboto-Light.ttf
djadmin/static/admin/font/roboto/Roboto-Light.woff
djadmin/static/admin/font/roboto/Roboto-Light.woff2
djadmin/static/admin/font/roboto/Roboto-Medium.ttf
djadmin/static/admin/font/roboto/Roboto-Medium.woff
djadmin/static/admin/font/roboto/Roboto-Medium.woff2
djadmin/static/admin/font/roboto/Roboto-Regular.ttf
djadmin/static/admin/font/roboto/Roboto-Regular.woff
djadmin/static/admin/font/roboto/Roboto-Regular.woff2
djadmin/static/admin/font/roboto/Roboto-Thin.ttf
djadmin/static/admin/font/roboto/Roboto-Thin.woff
djadmin/static/admin/font/roboto/Roboto-Thin.woff2
djadmin/static/admin/images/avatar.png
djadmin/static/admin/images/bot.png
djadmin/static/admin/images/mobile.png
djadmin/static/admin/images/pc.png
djadmin/static/admin/images/tablet.png
djadmin-1.1.6.dist-info/DESCRIPTION.rst
djadmin-1.1.6.dist-info/METADATA
djadmin-1.1.6.dist-info/RECORD
djadmin-1.1.6.dist-info/WHEEL
djadmin-1.1.6.dist-info/metadata.json
djadmin-1.1.6.dist-info/top_level.txt
