Metadata-Version: 2.0
Name: djadmin
Version: 1.1.6
Summary: Djadmin is a django admin theme
Home-page: https://github.com/sainipray/djadmin
Author: Neeraj Kumar
Author-email: sainineeraj1234@gmail.com
License: MIT
Platform: any
Classifier: Development Status :: 4 - Beta
Classifier: Framework :: Django
Classifier: Framework :: Django :: 1.9
Classifier: Framework :: Django :: 1.10
Classifier: Environment :: Web Environment
Classifier: Intended Audience :: Developers
Classifier: Intended Audience :: System Administrators
Classifier: License :: OSI Approved :: MIT License
Classifier: Operating System :: OS Independent
Classifier: Programming Language :: Python
Classifier: Programming Language :: Python :: 2.7
Classifier: Programming Language :: Python :: 3
Classifier: Programming Language :: Python :: 3.4
Classifier: Programming Language :: Python :: 3.5
Classifier: Topic :: Software Development
Classifier: Topic :: Software Development :: User Interfaces
Classifier: Topic :: System :: Systems Administration
Requires-Dist: geocoder
Requires-Dist: user-agents
